mesh_toolkit/README.md
mesh_toolkit/__init__.py
mesh_toolkit/animate.py
mesh_toolkit/animations.py
mesh_toolkit/base.py
mesh_toolkit/jobs.py
mesh_toolkit/logging.py
mesh_toolkit/models.py
mesh_toolkit/retexture.py
mesh_toolkit/rigging.py
mesh_toolkit/text3d.py
mesh_toolkit/agent_tools/__init__.py
mesh_toolkit/agent_tools/base.py
mesh_toolkit/agent_tools/registry.py
mesh_toolkit/agent_tools/tools.py
mesh_toolkit/agent_tools/crewai/__init__.py
mesh_toolkit/agent_tools/crewai/provider.py
mesh_toolkit/agent_tools/mcp/__init__.py
mesh_toolkit/agent_tools/mcp/__main__.py
mesh_toolkit/agent_tools/mcp/provider.py
mesh_toolkit/persistence/__init__.py
mesh_toolkit/persistence/repository.py
mesh_toolkit/persistence/schemas.py
mesh_toolkit/persistence/utils.py
mesh_toolkit/persistence/vector_store.py
mesh_toolkit/webhooks/__init__.py
mesh_toolkit/webhooks/handler.py
mesh_toolkit/webhooks/schemas.py
mesh_toolkit-0.1.0.dist-info/METADATA
mesh_toolkit-0.1.0.dist-info/WHEEL
mesh_toolkit-0.1.0.dist-info/entry_points.txt
mesh_toolkit-0.1.0.dist-info/RECORD
