Metadata-Version: 2.4
Name: mesh-toolkit
Version: 0.1.0
Summary: Python SDK for Meshy AI 3D asset generation API
Project-URL: Homepage, https://github.com/jbcom/jbcom-oss-ecosystem
Project-URL: Repository, https://github.com/jbcom/jbcom-oss-ecosystem/tree/main/packages/mesh-toolkit
Project-URL: Documentation, https://github.com/jbcom/jbcom-oss-ecosystem/tree/main/packages/mesh-toolkit#readme
Author-email: jbcom <jbogaty@gmail.com>
License: MIT
Keywords: 3d,ai,game-assets,glb,meshy,procedural-generation
Classifier: Development Status :: 3 - Alpha
Classifier: Intended Audience :: Developers
Classifier: License :: OSI Approved :: MIT License
Classifier: Programming Language :: Python :: 3
Classifier: Programming Language :: Python :: 3.9
Classifier: Programming Language :: Python :: 3.10
Classifier: Programming Language :: Python :: 3.11
Classifier: Programming Language :: Python :: 3.12
Classifier: Programming Language :: Python :: 3.13
Classifier: Topic :: Games/Entertainment
Classifier: Topic :: Multimedia :: Graphics :: 3D Modeling
Requires-Python: >=3.9
Requires-Dist: eval-type-backport>=0.2.0; python_version < '3.10'
Requires-Dist: httpx>=0.28.1
Requires-Dist: pydantic>=2.0.0
Requires-Dist: rich>=14.0.0
Requires-Dist: tenacity>=9.1.2
Provides-Extra: agents
Requires-Dist: crewai[tools]>=1.5.0; extra == 'agents'
Requires-Dist: mcp>=1.0.0; extra == 'agents'
Provides-Extra: all
Requires-Dist: crewai[tools]>=1.5.0; extra == 'all'
Requires-Dist: fastapi>=0.115.0; extra == 'all'
Requires-Dist: mcp>=1.0.0; extra == 'all'
Requires-Dist: pyngrok>=7.2.2; extra == 'all'
Requires-Dist: sentence-transformers>=3.0.0; extra == 'all'
Requires-Dist: sqlite-vec>=0.1.0; extra == 'all'
Requires-Dist: uvicorn>=0.38.0; extra == 'all'
Provides-Extra: crewai
Requires-Dist: crewai[tools]>=1.5.0; extra == 'crewai'
Provides-Extra: dev
Requires-Dist: beautifulsoup4>=4.12.0; extra == 'dev'
Provides-Extra: mcp
Requires-Dist: mcp>=1.0.0; extra == 'mcp'
Provides-Extra: tests
Requires-Dist: pytest-asyncio>=0.23.0; extra == 'tests'
Requires-Dist: pytest-cov>=5.0.0; extra == 'tests'
Requires-Dist: pytest-mock>=3.14.0; extra == 'tests'
Requires-Dist: pytest>=8.0.0; extra == 'tests'
Provides-Extra: vector
Requires-Dist: sentence-transformers>=3.0.0; extra == 'vector'
Requires-Dist: sqlite-vec>=0.1.0; extra == 'vector'
Provides-Extra: webhooks
Requires-Dist: fastapi>=0.115.0; extra == 'webhooks'
Requires-Dist: pyngrok>=7.2.2; extra == 'webhooks'
Requires-Dist: uvicorn>=0.38.0; extra == 'webhooks'
